README.rst
setup.py
django_sortedone2many.egg-info/PKG-INFO
django_sortedone2many.egg-info/SOURCES.txt
django_sortedone2many.egg-info/dependency_links.txt
django_sortedone2many.egg-info/not-zip-safe
django_sortedone2many.egg-info/requires.txt
django_sortedone2many.egg-info/top_level.txt
sortedone2many/__init__.py
sortedone2many/admin.py
sortedone2many/fields.py
sortedone2many/forms.py
sortedone2many/utils.py