Metadata-Version: 1.1
Name: django-sortedone2many
Version: 0.1.6
Summary: Provide a one-to-many relationship that also remembers the order of related objects.
Home-page: https://github.com/ShenggaoZhu/django-sortedone2many
Author: Shenggao Zhu
Author-email: zshgao@gmail.com
License: MIT
Download-URL: https://codeload.github.com/ShenggaoZhu/django-sortedone2many/zip/v0.1.6
Keywords: django,model,field,one-to-many,SortedOneToManyField
Platform: UNKNOWN
Classifier: Development Status :: 4 - Beta
Classifier: Environment :: Web Environment
Classifier: Framework :: Django
Classifier: Intended Audience :: Developers
Classifier: License :: OSI Approved :: BSD License
Classifier: Natural Language :: English
Classifier: Operating System :: OS Independent
Classifier: Programming Language :: Python
Classifier: Programming Language :: Python :: 3.4
Classifier: Programming Language :: Python :: 3.5
